MANIFEST.in
README.rst
markdowndotnet.py
requirements.txt
setup.py
markdowndotnet.egg-info/PKG-INFO
markdowndotnet.egg-info/SOURCES.txt
markdowndotnet.egg-info/dependency_links.txt
markdowndotnet.egg-info/entry_points.txt
markdowndotnet.egg-info/requires.txt
markdowndotnet.egg-info/top_level.txt